{"equity": 100000.0, "daily_pnl": 0.0, "drawdown_pct": 0.0, "kill_switch_active": false, "open_positions_count": 0, "trade_count": 0, "win_rate": 0.0, "equity_history": [{"t": "2026-06-23T08:14:25.912159", "v": 100000.0}], "positions": [], "recent_trades": [], "latest_signals": {"BTC/USD": {"signal": "HOLD", "confidence": 0.3829469191814637}, "ETH/USD": {"signal": "HOLD", "confidence": 0.422124320232808}, "SOL/USD": {"signal": "HOLD", "confidence": 0.4698354583654442}, "DOGE/USD": {"signal": "HOLD", "confidence": 0.3602986091095412}, "LTC/USD": {"signal": "HOLD", "confidence": 0.4323345618108818}, "BCH/USD": {"signal": "HOLD", "confidence": 0.4063756606989443}, "AVAX/USD": {"signal": "HOLD", "confidence": 0.3593221184626884}, "LINK/USD": {"signal": "HOLD", "confidence": 0.422124320232808}}}